LICENSE
chilean_rut/__init__.py
chilean_rut/chilean_rut.py
chilean_rut-0.1.3.dist-info/entry_points.txt
chilean_rut-0.1.3.dist-info/LICENSE
chilean_rut-0.1.3.dist-info/WHEEL
chilean_rut-0.1.3.dist-info/METADATA
chilean_rut-0.1.3.dist-info/RECORD
