Metadata-Version: 2.1
Name: chilean-rut
Version: 0.1.3
Summary: Module to validate, format, clean and get verification digit for Chileans RUT numbers
Home-page: https://github.com/rafaelsuarezg/chilean_rut
License: MIT
Keywords: rut,run,chile,chilean
Author: Rafael Suarez
Author-email: rafael.asg@gmail.com
Requires-Python: >=3.6,<4.0
Classifier: Environment :: Plugins
Classifier: License :: OSI Approved :: MIT License
Classifier: Operating System :: OS Independent
Classifier: Programming Language :: Python
Classifier: Programming Language :: Python :: 3
Classifier: Programming Language :: Python :: 3.10
Classifier: Programming Language :: Python :: 3.6
Classifier: Programming Language :: Python :: 3.7
Classifier: Programming Language :: Python :: 3.8
Classifier: Programming Language :: Python :: 3.9
Classifier: Topic :: Software Development :: Libraries :: Python Modules
Project-URL: Repository, https://github.com/rafaelsuarezg/chilean_rut
